{
  "data": [
    { 
      "category": 0, 
      "id":   0, 
      "name": "Hot Mulled Cider", 
      "ingredients": [
        "",
        ""
      ], 
      "instructions": [
        "",
        ""
      ]
    },
    { 
      "category": 0, 
      "id":   1, 
      "name": "Cranberry Tea", 
      "ingredients": [
        "",
        ""
      ], 
      "instructions": [
        "",
        ""
      ]
    },
    { 
      "category": 0, 
      "id":   2, 
      "name": "Hot Cocoa Mix", 
      "ingredients": [
        "",
        ""
      ], 
      "instructions": [
        "",
        ""
      ]
    },
    { 
      "category": 0, 
      "id":   3, 
      "name": "Cindy Smith's Punch", 
      "ingredients": [
        "",
        ""
      ], 
      "instructions": [
        "",
        ""
      ]
    },
    { 
      "category": 0, 
      "id":   4, 
      "name": "7-Up Punch", 
      "ingredients": [
        "",
        ""
      ], 
      "instructions": [
        "",
        ""
      ]
    },
    { 
      "category": 0, 
      "id":   5, 
      "name": "Orange Rind Curls", 
      "ingredients": [
        "",
        ""
      ], 
      "instructions": [
        "",
        ""
      ]
    },
    { 
      "category": 0, 
      "id":   6, 
      "name": "Slush Sparkle", 
      "ingredients": [
        "",
        ""
      ], 
      "instructions": [
        "",
        ""
      ]
    },
    { 
      "category": 0, 
      "id":   7, 
      "name": "Tomato Cocktail", 
      "ingredients": [
        "",
        ""
      ], 
      "instructions": [
        "",
        ""
      ]
    },
    { 
      "category": 0, 
      "id":   8, 
      "name": "Fruit Smoothies", 
      "ingredients": [
        "",
        ""
      ], 
      "instructions": [
        "",
        ""
      ]
    },
    { 
      "category": 0, 
      "id":   9, 
      "name": "White Grape Punch", 
      "ingredients": [
        "",
        ""
      ], 
      "instructions": [
        "",
        ""
      ]
    },
    { 
      "category": 0, 
      "id":  10, 
      "name": "Summertime Slush", 
      "ingredients": [
        "",
        ""
      ], 
      "instructions": [
        "",
        ""
      ]
    },
    { 
      "category": 0, 
      "id":  11, 
      "name": "Chai Tea", 
      "ingredients": [
        "",
        ""
      ], 
      "instructions": [
        "",
        ""
      ]
    },
    {
      "category": 1, 
      "id":  12, 
      "name": "Hot Spinach Artichocke Dip", 
      "ingredients": [
        "",
        ""
      ], 
      "instructions": [
        "",
        ""
      ]
    },
    { 
      "category": 1, 
      "id":  13, 
      "name": "Fresh Fruit Dip", 
      "ingredients": [
        "",
        ""
      ], 
      "instructions": [
        "",
        ""
      ]
    },
    { 
      "category": 1, 
      "id":  14, 
      "name": "Chestnuts", 
      "ingredients": [
        "",
        ""
      ], 
      "instructions": [
        "",
        ""
      ]
    },
    { 
      "category": 1, 
      "id":  15, 
      "name": "Cheese Ball", 
      "ingredients": [
        "",
        ""
      ], 
      "instructions": [
        "",
        ""
      ]
    },
    { 
      "category": 1, 
      "id":  16, 
      "name": "Little Smokies", 
      "ingredients": [
        "",
        ""
      ], 
      "instructions": [
        "",
        ""
      ]
    },
    { 
      "category": 1, 
      "id":  17, 
      "name": "Reuben Spread", 
      "ingredients": [
        "",
        ""
      ], 
      "instructions": [
        "",
        ""
      ]
    },
    { 
      "category": 1, 
      "id":  18, 
      "name": "Cheese Dreams", 
      "ingredients": [
        "",
        ""
      ], 
      "instructions": [
        "",
        ""
      ]
    },
    { 
      "category": 1, 
      "id":  19, 
      "name": "Taco Salad", 
      "ingredients": [
        "",
        ""
      ], 
      "instructions": [
        "",
        ""
      ]
    },
    { 
      "category": 1, 
      "id":  20, 
      "name": "Vegetable Dip", 
      "ingredients": [
        "",
        ""
      ], 
      "instructions": [
        "",
        ""
      ]
    },
    { 
      "category": 1, 
      "id":  21, 
      "name": "Fruit Dip", 
      "ingredients": [
        "",
        ""
      ], 
      "instructions": [
        "",
        ""
      ]
    },
    { 
      "category": 1, 
      "id":  22, 
      "name": "Caramel Apple Dip", 
      "ingredients": [
        "",
        ""
      ], 
      "instructions": [
        "",
        ""
      ]
    },
    { 
      "category": 1, 
      "id":  23, 
      "name": "Apple Snickers", 
      "ingredients": [
        "",
        ""
      ], 
      "instructions": [
        "",
        ""
      ]
    },
    { 
      "category": 1, 
      "id":  24, 
      "name": "Nuts And Bolts", 
      "ingredients": [
        "",
        ""
      ], 
      "instructions": [
        "",
        ""
      ]
    },
    { 
      "category": 1, 
      "id":  25, 
      "name": "Joni's Wedding Chex Mix", 
      "ingredients": [
        "",
        ""
      ], 
      "instructions": [
        "",
        ""
      ]
    },
    { 
      "category": 1, 
      "id":  26, 
      "name": "Spinach Dip in a Bread Bowl", 
      "ingredients": [
        "",
        ""
      ], 
      "instructions": [
        "",
        ""
      ]
    },
    { 
      "category": 1, 
      "id":  27, 
      "name": "Chicken Pillows", 
      "ingredients": [
        "",
        ""
      ], 
      "instructions": [
        "",
        ""
      ]
    },
    {
      "category": 2, 
      "id":  28, 
      "name": "Bar-B-Q Ribs", 
      "ingredients": [
        "",
        ""
      ], 
      "instructions": [
        "",
        ""
      ]
    },
    { 
      "category": 2, 
      "id":  29, 
      "name": "Taco Casserole", 
      "ingredients": [
        "",
        ""
      ], 
      "instructions": [
        "",
        ""
      ]
    },
    { 
      "category": 2, 
      "id":  30, 
      "name": "Corn Beef Casserole", 
      "ingredients": [
        "",
        ""
      ], 
      "instructions": [
        "",
        ""
      ]
    },
    { 
      "category": 2, 
      "id":  31, 
      "name": "Frikadellas (Norwegian Meatballs)", 
      "ingredients": [
        "",
        ""
      ], 
      "instructions": [
        "",
        ""
      ]
    },
    { 
      "category": 2, 
      "id":  32, 
      "name": "Stuffed Peppers", 
      "ingredients": [
        "",
        ""
      ], 
      "instructions": [
        "",
        ""
      ]
    },
    { 
      "category": 2, 
      "id":  33, 
      "name": "Reuben Loaf", 
      "ingredients": [
        "",
        ""
      ], 
      "instructions": [
        "",
        ""
      ]
    },
    { 
      "category": 2, 
      "id":  34, 
      "name": "Sloppy Joe", 
      "ingredients": [
        "",
        ""
      ], 
      "instructions": [
        "",
        ""
      ]
    },
    { 
      "category": 2, 
      "id":  35, 
      "name": "Chop Suey Casserole", 
      "ingredients": [
        "",
        ""
      ], 
      "instructions": [
        "",
        ""
      ]
    },
    { 
      "category": 2, 
      "id":  36, 
      "name": "Belly Burner Meat Balls", 
      "ingredients": [
        "",
        ""
      ], 
      "instructions": [
        "",
        ""
      ]
    },
    { 
      "category": 2, 
      "id":  37, 
      "name": "Hamburger Pie", 
      "ingredients": [
        "",
        ""
      ], 
      "instructions": [
        "",
        ""
      ]
    },
    { 
      "category": 2, 
      "id":  38, 
      "name": "Oven Swedish Meatballs", 
      "ingredients": [
        "",
        ""
      ], 
      "instructions": [
        "",
        ""
      ]
    },
    { 
      "category": 2, 
      "id":  39, 
      "name": "Brown's BBQ Beef Supreme Sloppy Joes", 
      "ingredients": [
        "",
        ""
      ], 
      "instructions": [
        "",
        ""
      ]
    },
    { 
      "category": 2, 
      "id":  40, 
      "name": "Beautiful Baked Ziti", 
      "ingredients": [
        "",
        ""
      ], 
      "instructions": [
        "",
        ""
      ]
    },
    { 
      "category": 2, 
      "id":  41, 
      "name": "Beef Stroganoff", 
      "ingredients": [
        "",
        ""
      ], 
      "instructions": [
        "",
        ""
      ]
    },
    { 
      "category": 2, 
      "id":  42, 
      "name": "Tater Tot Casserole", 
      "ingredients": [
        "",
        ""
      ], 
      "instructions": [
        "",
        ""
      ]
    },
    { 
      "category": 2, 
      "id":  43, 
      "name": "Colorado Pie", 
      "ingredients": [
        "",
        ""
      ], 
      "instructions": [
        "",
        ""
      ]
    },
    { 
      "category": 2, 
      "id":  44, 
      "name": "Pizza Style Fondue", 
      "ingredients": [
        "",
        ""
      ], 
      "instructions": [
        "",
        ""
      ]
    },
    { 
      "category": 2, 
      "id":  45, 
      "name": "Kathy's Spaghetti Sauce", 
      "ingredients": [
        "",
        ""
      ], 
      "instructions": [
        "",
        ""
      ]
    },
    { 
      "category": 2, 
      "id":  46, 
      "name": "Diane's Thick Pan Pizza", 
      "ingredients": [
        "",
        ""
      ], 
      "instructions": [
        "",
        ""
      ]
    },
    { 
      "category": 2, 
      "id":  47, 
      "name": "Stir Fried Beef and Broccoli", 
      "ingredients": [
        "",
        ""
      ], 
      "instructions": [
        "",
        ""
      ]
    },
    { 
      "category": 2, 
      "id":  48, 
      "name": "Rice and Peanut Gravy Beef", 
      "ingredients": [
        "",
        ""
      ], 
      "instructions": [
        "",
        ""
      ]
    },
    { 
      "category": 2, 
      "id":  49, 
      "name": "Easy Pork Chops", 
      "ingredients": [
        "",
        ""
      ], 
      "instructions": [
        "",
        ""
      ]
    },
    { 
      "category": 2, 
      "id":  50, 
      "name": "Ham and Spaghetti", 
      "ingredients": [
        "",
        ""
      ], 
      "instructions": [
        "",
        ""
      ]
    },
    { 
      "category": 2, 
      "id":  51, 
      "name": "Chicken Salad", 
      "ingredients": [
        "",
        ""
      ], 
      "instructions": [
        "",
        ""
      ]
    },
    { 
      "category": 2, 
      "id":  52, 
      "name": "Cheesy Ham and Broccoli Casserole", 
      "ingredients": [
        "",
        ""
      ], 
      "instructions": [
        "",
        ""
      ]
    },
    { 
      "category": 2, 
      "id":  53, 
      "name": "Creamy Italian Chicken", 
      "ingredients": [
        "",
        ""
      ], 
      "instructions": [
        "",
        ""
      ]
    },
    { 
      "category": 2, 
      "id":  54, 
      "name": "Chili-Cheese Black Bean Enchiladas", 
      "ingredients": [
        "",
        ""
      ], 
      "instructions": [
        "",
        ""
      ]
    },
    { 
      "category": 2, 
      "id":  55, 
      "name": "Honey Baked Chicken", 
      "ingredients": [
        "",
        ""
      ], 
      "instructions": [
        "",
        ""
      ]
    },
    { 
      "category": 2, 
      "id":  56, 
      "name": "Chicken and Broccoli Casserole", 
      "ingredients": [
        "",
        ""
      ], 
      "instructions": [
        "",
        ""
      ]
    },
    { 
      "category": 2, 
      "id":  57, 
      "name": "Turkey Tetrazzini", 
      "ingredients": [
        "",
        ""
      ], 
      "instructions": [
        "",
        ""
      ]
    },
    { 
      "category": 2, 
      "id":  58, 
      "name": "Chicken Rolls", 
      "ingredients": [
        "",
        ""
      ], 
      "instructions": [
        "",
        ""
      ]
    },
    { 
      "category": 2, 
      "id":  59, 
      "name": "Lasanga Primavera", 
      "ingredients": [
        "",
        ""
      ], 
      "instructions": [
        "",
        ""
      ]
    },
    { 
      "category": 2, 
      "id":  60, 
      "name": "California Chicken - Crock Pot", 
      "ingredients": [
        "",
        ""
      ], 
      "instructions": [
        "",
        ""
      ]
    },
    { 
      "category": 2, 
      "id":  61, 
      "name": "Chicken Alfredo Lasanga", 
      "ingredients": [
        "",
        ""
      ], 
      "instructions": [
        "",
        ""
      ]
    },
    { 
      "category": 2, 
      "id":  62, 
      "name": "Chicken Couscous", 
      "ingredients": [
        "",
        ""
      ], 
      "instructions": [
        "",
        ""
      ]
    },
    { 
      "category": 2, 
      "id":  63, 
      "name": "Holly's Impossible Chicken Broccoli Pie", 
      "ingredients": [
        "",
        ""
      ], 
      "instructions": [
        "",
        ""
      ]
    },
    { 
      "category": 2, 
      "id":  64, 
      "name": "Kathy's Chicken and Rice", 
      "ingredients": [
        "",
        ""
      ], 
      "instructions": [
        "",
        ""
      ]
    },
    { 
      "category": 2, 
      "id":  65, 
      "name": "Kathy's Tacos de Gallina", 
      "ingredients": [
        "",
        ""
      ], 
      "instructions": [
        "",
        ""
      ]
    },
    { 
      "category": 2, 
      "id":  66, 
      "name": "Tomato-Basil Chicken", 
      "ingredients": [
        "",
        ""
      ], 
      "instructions": [
        "",
        ""
      ]
    },
    { 
      "category": 2, 
      "id":  67, 
      "name": "Fettuccine and Chicken in Herb Sauce", 
      "ingredients": [
        "",
        ""
      ], 
      "instructions": [
        "",
        ""
      ]
    },
    { 
      "category": 2, 
      "id":  68, 
      "name": "Thai Chicken and Cashews", 
      "ingredients": [
        "",
        ""
      ], 
      "instructions": [
        "",
        ""
      ]
    },
    { 
      "category": 2, 
      "id":  69, 
      "name": "Frozen Fruit Cup", 
      "ingredients": [
        "",
        ""
      ], 
      "instructions": [
        "",
        ""
      ]
    },
    { 
      "category": 2, 
      "id":  70, 
      "name": "Chicken and Vegetable Lasagna - Crock Pot", 
      "ingredients": [
        "",
        ""
      ], 
      "instructions": [
        "",
        ""
      ]
    },
    { 
      "category": 2, 
      "id":  71, 
      "name": "Chicken Sate with Ponzu Sauce", 
      "ingredients": [
        "",
        ""
      ], 
      "instructions": [
        "",
        ""
      ]
    },
    { 
      "category": 2, 
      "id":  72, 
      "name": "Chicken Mushroom Crepes", 
      "ingredients": [
        "",
        ""
      ], 
      "instructions": [
        "",
        ""
      ]
    },
    { 
      "category": 2, 
      "id":  73, 
      "name": "Marinade for Tri-tip", 
      "ingredients": [
        "",
        ""
      ], 
      "instructions": [
        "",
        ""
      ]
    },
    {
      "category": 3, 
      "id":  74, 
      "name": "Lettuce and Mandarine Orange Salad", 
      "ingredients": [
        "",
        ""
      ], 
      "instructions": [
        "",
        ""
      ]
    },
    { 
      "category": 3, 
      "id":  75, 
      "name": "Linda's Sweet and Sour Dressing", 
      "ingredients": [
        "",
        ""
      ], 
      "instructions": [
        "",
        ""
      ]
    },
    { 
      "category": 3, 
      "id":  76, 
      "name": "Korean Salad", 
      "ingredients": [
        "",
        ""
      ], 
      "instructions": [
        "",
        ""
      ]
    },
    { 
      "category": 3, 
      "id":  77, 
      "name": "Gourmet Salad", 
      "ingredients": [
        "",
        ""
      ], 
      "instructions": [
        "",
        ""
      ]
    },
    { 
      "category": 3, 
      "id":  78, 
      "name": "Layered Overnight Salad", 
      "ingredients": [
        "",
        ""
      ], 
      "instructions": [
        "",
        ""
      ]
    },
    { 
      "category": 4, 
      "id":  79, 
      "name": "Sweet Potato Hash", 
      "ingredients": [
        "",
        ""
      ], 
      "instructions": [
        "",
        ""
      ]
    },
    { 
      "category": 4, 
      "id":  80, 
      "name": "Au Gratin Potatoes", 
      "ingredients": [
        "",
        ""
      ], 
      "instructions": [
        "",
        ""
      ]
    },
    { 
      "category": 4, 
      "id":  81, 
      "name": "Mashed Potato Casserole", 
      "ingredients": [
        "",
        ""
      ], 
      "instructions": [
        "",
        ""
      ]
    },
    { 
      "category": 4, 
      "id":  82, 
      "name": "Pizza Potatoes", 
      "ingredients": [
        "",
        ""
      ], 
      "instructions": [
        "",
        ""
      ]
    },
    { 
      "category": 4, 
      "id":  83, 
      "name": "Hidden Valley Ranch Potatoes", 
      "ingredients": [
        "",
        ""
      ], 
      "instructions": [
        "",
        ""
      ]
    },
    { 
      "category": 4, 
      "id":  84, 
      "name": "Banana Pineapple Salad", 
      "ingredients": [
        "",
        ""
      ], 
      "instructions": [
        "",
        ""
      ]
    },
    { 
      "category": 4, 
      "id":  85, 
      "name": "7-Up Salad", 
      "ingredients": [
        "",
        ""
      ], 
      "instructions": [
        "",
        ""
      ]
    },
    { 
      "category": 4, 
      "id":  86, 
      "name": "Linda's Sparkling Fruit Mold", 
      "ingredients": [
        "",
        ""
      ], 
      "instructions": [
        "",
        ""
      ]
    },
    { 
      "category": 4, 
      "id":  87, 
      "name": "Mississippi Corn Bread Salad", 
      "ingredients": [
        "",
        ""
      ], 
      "instructions": [
        "",
        ""
      ]
    },
    { 
      "category": 4, 
      "id":  88, 
      "name": "Ramen Noodle Salad", 
      "ingredients": [
        "",
        ""
      ], 
      "instructions": [
        "",
        ""
      ]
    },
    { 
      "category": 4, 
      "id":  89, 
      "name": "Marilee's 3 Bean Salad", 
      "ingredients": [
        "",
        ""
      ], 
      "instructions": [
        "",
        ""
      ]
    },
    { 
      "category": 4, 
      "id":  90, 
      "name": "Ann's Fruit Salad", 
      "ingredients": [
        "",
        ""
      ], 
      "instructions": [
        "",
        ""
      ]
    },
    { 
      "category": 4, 
      "id":  91, 
      "name": "Vegetable Salad", 
      "ingredients": [
        "",
        ""
      ], 
      "instructions": [
        "",
        ""
      ]
    },
    { 
      "category": 4, 
      "id":  92, 
      "name": "Marinated Vegetables", 
      "ingredients": [
        "",
        ""
      ], 
      "instructions": [
        "",
        ""
      ]
    },
    { 
      "category": 4, 
      "id":  93, 
      "name": "Marilee's Broccoli and Grape Salad", 
      "ingredients": [
        "",
        ""
      ], 
      "instructions": [
        "",
        ""
      ]
    },
    { 
      "category": 4, 
      "id":  94, 
      "name": "German Potato Salad", 
      "ingredients": [
        "",
        ""
      ], 
      "instructions": [
        "",
        ""
      ]
    },
    { 
      "category": 4, 
      "id":  95, 
      "name": "Susie's Vegetable Casserole", 
      "ingredients": [
        "",
        ""
      ], 
      "instructions": [
        "",
        ""
      ]
    },
    { 
      "category": 4, 
      "id":  96, 
      "name": "Candied Sweet Potatoes", 
      "ingredients": [
        "",
        ""
      ], 
      "instructions": [
        "",
        ""
      ]
    },
    { 
      "category": 4, 
      "id":  97, 
      "name": "Green Bean Casserole", 
      "ingredients": [
        "",
        ""
      ], 
      "instructions": [
        "",
        ""
      ]
    },
    { 
      "category": 4, 
      "id":  98, 
      "name": "Linda's Cheesy Broccoli Bake", 
      "ingredients": [
        "",
        ""
      ], 
      "instructions": [
        "",
        ""
      ]
    },
    { 
      "category": 4, 
      "id":  99, 
      "name": "Onion Pie", 
      "ingredients": [
        "",
        ""
      ], 
      "instructions": [
        "",
        ""
      ]
    },
    { 
      "category": 4, 
      "id": 100, 
      "name": "Chi-Chi's Sweet Corn Cake", 
      "ingredients": [
        "",
        ""
      ], 
      "instructions": [
        "",
        ""
      ]
    },
    { 
      "category": 4, 
      "id": 101, 
      "name": "Zucchini Casserole", 
      "ingredients": [
        "",
        ""
      ], 
      "instructions": [
        "",
        ""
      ]
    },
    { 
      "category": 4, 
      "id": 102, 
      "name": "Linda's 5 Way Beans", 
      "ingredients": [
        "",
        ""
      ], 
      "instructions": [
        "",
        ""
      ]
    },
    { 
      "category": 4, 
      "id": 103, 
      "name": "Marilee's Golden Cheddar Broccoli Bake", 
      "ingredients": [
        "",
        ""
      ], 
      "instructions": [
        "",
        ""
      ]
    },
    { 
      "category": 4, 
      "id": 104, 
      "name": "Marilee's Calico Beans", 
      "ingredients": [
        "",
        ""
      ], 
      "instructions": [
        "",
        ""
      ]
    },
    { 
      "category": 4, 
      "id": 105, 
      "name": "Diane's Del Monico Potatoes", 
      "ingredients": [
        "",
        ""
      ], 
      "instructions": [
        "",
        ""
      ]
    },
    { 
      "category": 4, 
      "id": 106, 
      "name": "Boston Baked Beans", 
      "ingredients": [
        "",
        ""
      ], 
      "instructions": [
        "",
        ""
      ]
    },
    { 
      "category": 4, 
      "id": 107, 
      "name": "Diane's Carrot Casserole", 
      "ingredients": [
        "",
        ""
      ], 
      "instructions": [
        "",
        ""
      ]
    },
    { 
      "category": 4, 
      "id": 108, 
      "name": "Linda's Super Rice", 
      "ingredients": [
        "",
        ""
      ], 
      "instructions": [
        "",
        ""
      ]
    },
    { 
      "category": 4, 
      "id": 109, 
      "name": "Kathryn's Pickled Beets", 
      "ingredients": [
        "",
        ""
      ], 
      "instructions": [
        "",
        ""
      ]
    },
    { 
      "category": 4, 
      "id": 110, 
      "name": "Gary and Beas's Pickles", 
      "ingredients": [
        "",
        ""
      ], 
      "instructions": [
        "",
        ""
      ]
    },
    { 
      "category": 4, 
      "id": 111, 
      "name": "Candied Dill Pickles", 
      "ingredients": [
        "",
        ""
      ], 
      "instructions": [
        "",
        ""
      ]
    },
    { 
      "category": 4, 
      "id": 112, 
      "name": "VCY Refrigerator Pickles", 
      "ingredients": [
        "",
        ""
      ], 
      "instructions": [
        "",
        ""
      ]
    },
    {
      "category": 5, 
      "id": 113, 
      "name": "Wild Rice Soup", 
      "ingredients": [
        "",
        ""
      ], 
      "instructions": [
        "",
        ""
      ]
    },
    { 
      "category": 5, 
      "id": 114, 
      "name": "Taco Soup", 
      "ingredients": [
        "",
        ""
      ], 
      "instructions": [
        "",
        ""
      ]
    },
    { 
      "category": 5, 
      "id": 115, 
      "name": "Taco Soup", 
      "ingredients": [
        "",
        ""
      ], 
      "instructions": [
        "",
        ""
      ]
    },
    { 
      "category": 5, 
      "id": 116, 
      "name": "Creamy Onion Spinach Soup", 
      "ingredients": [
        "",
        ""
      ], 
      "instructions": [
        "",
        ""
      ]
    },
    { 
      "category": 5, 
      "id": 117, 
      "name": "Cheese-Broccoli Soup", 
      "ingredients": [
        "",
        ""
      ], 
      "instructions": [
        "",
        ""
      ]
    },
    { 
      "category": 5, 
      "id": 118, 
      "name": "Dad's Vegetable Soup", 
      "ingredients": [
        "",
        ""
      ], 
      "instructions": [
        "",
        ""
      ]
    },
    { 
      "category": 5, 
      "id": 119, 
      "name": "Carrot Jalapeno Soup", 
      "ingredients": [
        "",
        ""
      ], 
      "instructions": [
        "",
        ""
      ]
    },
    { 
      "category": 5, 
      "id": 120, 
      "name": "She Crab Soup", 
      "ingredients": [
        "",
        ""
      ], 
      "instructions": [
        "",
        ""
      ]
    },
    { 
      "category": 5, 
      "id": 121, 
      "name": "Souper Chili", 
      "ingredients": [
        "",
        ""
      ], 
      "instructions": [
        "",
        ""
      ]
    },
    {
      "category": 6, 
      "id": 122, 
      "name": "Pizza Dough", 
      "ingredients": [
        "",
        ""
      ], 
      "instructions": [
        "",
        ""
      ]
    },
    { 
      "category": 6, 
      "id": 123, 
      "name": "Marilee's Zucchini Bread", 
      "ingredients": [
        "",
        ""
      ], 
      "instructions": [
        "",
        ""
      ]
    },
    { 
      "category": 6, 
      "id": 124, 
      "name": "Honey Buns", 
      "ingredients": [
        "",
        ""
      ], 
      "instructions": [
        "",
        ""
      ]
    },
    { 
      "category": 6, 
      "id": 125, 
      "name": "Holly's Potato Dough", 
      "ingredients": [
        "",
        ""
      ], 
      "instructions": [
        "",
        ""
      ]
    },
    { 
      "category": 6, 
      "id": 126, 
      "name": "Holly's Honey Whole Wheat Bread", 
      "ingredients": [
        "",
        ""
      ], 
      "instructions": [
        "",
        ""
      ]
    },
    { 
      "category": 6, 
      "id": 127, 
      "name": "Carmel Bubble Rolls", 
      "ingredients": [
        "",
        ""
      ], 
      "instructions": [
        "",
        ""
      ]
    },
    { 
      "category": 6, 
      "id": 128, 
      "name": "Grandma Conklyn's Cinnamon Rolls", 
      "ingredients": [
        "",
        ""
      ], 
      "instructions": [
        "",
        ""
      ]
    },
    { 
      "category": 6, 
      "id": 129, 
      "name": "Krantz", 
      "ingredients": [
        "",
        ""
      ], 
      "instructions": [
        "",
        ""
      ]
    },
    { 
      "category": 6, 
      "id": 130, 
      "name": "Banana Nut Bread", 
      "ingredients": [
        "",
        ""
      ], 
      "instructions": [
        "",
        ""
      ]
    },
    { 
      "category": 6, 
      "id": 131, 
      "name": "Christmas Stolen", 
      "ingredients": [
        "",
        ""
      ], 
      "instructions": [
        "",
        ""
      ]
    },
    { 
      "category": 6, 
      "id": 132, 
      "name": "Parmesan Rolls", 
      "ingredients": [
        "",
        ""
      ], 
      "instructions": [
        "",
        ""
      ]
    },
    { 
      "category": 6, 
      "id": 133, 
      "name": "Mom's Butterhorn Rolls", 
      "ingredients": [
        "",
        ""
      ], 
      "instructions": [
        "",
        ""
      ]
    },
    { 
      "category": 6, 
      "id": 134, 
      "name": "Kathy's Cranberry Bread", 
      "ingredients": [
        "",
        ""
      ], 
      "instructions": [
        "",
        ""
      ]
    },
    { 
      "category": 6, 
      "id": 135, 
      "name": "Mom's Banana Bread", 
      "ingredients": [
        "",
        ""
      ], 
      "instructions": [
        "",
        ""
      ]
    },
    { 
      "category": 6, 
      "id": 136, 
      "name": "Pumpkin Bread", 
      "ingredients": [
        "",
        ""
      ], 
      "instructions": [
        "",
        ""
      ]
    },
    { 
      "category": 6, 
      "id": 137, 
      "name": "Bran Muffins", 
      "ingredients": [
        "",
        ""
      ], 
      "instructions": [
        "",
        ""
      ]
    },
    { 
      "category": 6, 
      "id": 138, 
      "name": "Cranberry Almond Sour Cream Bread", 
      "ingredients": [
        "",
        ""
      ], 
      "instructions": [
        "",
        ""
      ]
    },
    { 
      "category": 6, 
      "id": 139, 
      "name": "Holly's Oatmeal Bread", 
      "ingredients": [
        "",
        ""
      ], 
      "instructions": [
        "",
        ""
      ]
    },
    { 
      "category": 6, 
      "id": 140, 
      "name": "Blueberry Oatmeal Muffins", 
      "ingredients": [
        "",
        ""
      ], 
      "instructions": [
        "",
        ""
      ]
    },
    { 
      "category": 7, 
      "id": 141, 
      "name": "Breakfast Egg-Souffle", 
      "ingredients": [
        "",
        ""
      ], 
      "instructions": [
        "",
        ""
      ]
    },
    { 
      "category": 7, 
      "id": 142, 
      "name": "Sunny Frittata", 
      "ingredients": [
        "",
        ""
      ], 
      "instructions": [
        "",
        ""
      ]
    },
    { 
      "category": 7, 
      "id": 143, 
      "name": "Crepes", 
      "ingredients": [
        "",
        ""
      ], 
      "instructions": [
        "",
        ""
      ]
    },
    { 
      "category": 7, 
      "id": 144, 
      "name": "Holly's Pancake Mix", 
      "ingredients": [
        "",
        ""
      ], 
      "instructions": [
        "",
        ""
      ]
    },
    { 
      "category": 7, 
      "id": 145, 
      "name": "Kathy's Whole Wheat Pancakes", 
      "ingredients": [
        "",
        ""
      ], 
      "instructions": [
        "",
        ""
      ]
    },
    { 
      "category": 7, 
      "id": 146, 
      "name": "Christmas Eggs", 
      "ingredients": [
        "",
        ""
      ], 
      "instructions": [
        "",
        ""
      ]
    },
    { 
      "category": 7, 
      "id": 147, 
      "name": "Scrambled Eggs and Noodles", 
      "ingredients": [
        "",
        ""
      ], 
      "instructions": [
        "",
        ""
      ]
    },
    { 
      "category": 7, 
      "id": 148, 
      "name": "Breakfast Casserole", 
      "ingredients": [
        "",
        ""
      ], 
      "instructions": [
        "",
        ""
      ]
    },
    { 
      "category": 7, 
      "id": 149, 
      "name": "Coffee Cake Streusel", 
      "ingredients": [
        "",
        ""
      ], 
      "instructions": [
        "",
        ""
      ]
    },
    { 
      "category": 8, 
      "id": 150, 
      "name": "Cake Cookies", 
      "ingredients": [
        "",
        ""
      ], 
      "instructions": [
        "",
        ""
      ]
    },
    { 
      "category": 8, 
      "id": 151, 
      "name": "Christmas Jello", 
      "ingredients": [
        "",
        ""
      ], 
      "instructions": [
        "",
        ""
      ]
    },
    { 
      "category": 8, 
      "id": 152, 
      "name": "Cartwheel Desserts", 
      "ingredients": [
        "",
        ""
      ], 
      "instructions": [
        "",
        ""
      ]
    },
    { 
      "category": 8, 
      "id": 153, 
      "name": "Key Lime Pie", 
      "ingredients": [
        "",
        ""
      ], 
      "instructions": [
        "",
        ""
      ]
    },
    { 
      "category": 8, 
      "id": 154, 
      "name": "Cherry or Blueberry Dessert", 
      "ingredients": [
        "",
        ""
      ], 
      "instructions": [
        "",
        ""
      ]
    },
    { 
      "category": 8, 
      "id": 155, 
      "name": "Fluffy Strawberry Frosting", 
      "ingredients": [
        "",
        ""
      ], 
      "instructions": [
        "",
        ""
      ]
    },
    { 
      "category": 8, 
      "id": 156, 
      "name": "Rhubarb Crunch", 
      "ingredients": [
        "",
        ""
      ], 
      "instructions": [
        "",
        ""
      ]
    },
    { 
      "category": 8, 
      "id": 157, 
      "name": "Linda's Pumpkin Pie Cake", 
      "ingredients": [
        "",
        ""
      ], 
      "instructions": [
        "",
        ""
      ]
    },
    { 
      "category": 8, 
      "id": 158, 
      "name": "Schaum Torte", 
      "ingredients": [
        "",
        ""
      ], 
      "instructions": [
        "",
        ""
      ]
    },
    { 
      "category": 8, 
      "id": 159, 
      "name": "Mexican Wedding Cake", 
      "ingredients": [
        "",
        ""
      ], 
      "instructions": [
        "",
        ""
      ]
    },
    { 
      "category": 8, 
      "id": 160, 
      "name": "Browned Butter Frosting", 
      "ingredients": [
        "",
        ""
      ], 
      "instructions": [
        "",
        ""
      ]
    },
    { 
      "category": 8, 
      "id": 161, 
      "name": "Texas Sheet Cake", 
      "ingredients": [
        "",
        ""
      ], 
      "instructions": [
        "",
        ""
      ]
    },
    { 
      "category": 8, 
      "id": 162, 
      "name": "Frosting for Texas Sheet Cake", 
      "ingredients": [
        "",
        ""
      ], 
      "instructions": [
        "",
        ""
      ]
    },
    { 
      "category": 8, 
      "id": 163, 
      "name": "Self Frosted Chocolate Bundt Cake", 
      "ingredients": [
        "",
        ""
      ], 
      "instructions": [
        "",
        ""
      ]
    },
    { 
      "category": 8, 
      "id": 164, 
      "name": "Orange Tapioca Jello", 
      "ingredients": [
        "",
        ""
      ], 
      "instructions": [
        "",
        ""
      ]
    },
    { 
      "category": 8, 
      "id": 165, 
      "name": "Reese Peanut Bars", 
      "ingredients": [
        "",
        ""
      ], 
      "instructions": [
        "",
        ""
      ]
    },
    { 
      "category": 8, 
      "id": 166, 
      "name": "Orange Delight", 
      "ingredients": [
        "",
        ""
      ], 
      "instructions": [
        "",
        ""
      ]
    },
    { 
      "category": 8, 
      "id": 167, 
      "name": "Lemon-Lime Cream Jello", 
      "ingredients": [
        "",
        ""
      ], 
      "instructions": [
        "",
        ""
      ]
    },
    { 
      "category": 8, 
      "id": 168, 
      "name": "Caramel Nutties", 
      "ingredients": [
        "",
        ""
      ], 
      "instructions": [
        "",
        ""
      ]
    },
    { 
      "category": 8, 
      "id": 169, 
      "name": "French Butter Horns", 
      "ingredients": [
        "",
        ""
      ], 
      "instructions": [
        "",
        ""
      ]
    },
    { 
      "category": 8, 
      "id": 170, 
      "name": "Oatmeal Carmel Bars", 
      "ingredients": [
        "",
        ""
      ], 
      "instructions": [
        "",
        ""
      ]
    },
    { 
      "category": 8, 
      "id": 171, 
      "name": "Lemon Bars", 
      "ingredients": [
        "",
        ""
      ], 
      "instructions": [
        "",
        ""
      ]
    },
    { 
      "category": 8, 
      "id": 172, 
      "name": "Kathy's Blonde Brownies", 
      "ingredients": [
        "",
        ""
      ], 
      "instructions": [
        "",
        ""
      ]
    },
    { 
      "category": 8, 
      "id": 173, 
      "name": "Chocolate Fudge Tarts", 
      "ingredients": [
        "",
        ""
      ], 
      "instructions": [
        "",
        ""
      ]
    },
    { 
      "category": 8, 
      "id": 174, 
      "name": "Chocolate Scotcheroos", 
      "ingredients": [
        "",
        ""
      ], 
      "instructions": [
        "",
        ""
      ]
    },
    { 
      "category": 8, 
      "id": 175, 
      "name": "California Dream Bars", 
      "ingredients": [
        "",
        ""
      ], 
      "instructions": [
        "",
        ""
      ]
    },
    { 
      "category": 8, 
      "id": 176, 
      "name": "Pumpkin Bars", 
      "ingredients": [
        "",
        ""
      ], 
      "instructions": [
        "",
        ""
      ]
    },
    { 
      "category": 8, 
      "id": 177, 
      "name": "Kathy's Brownie Recipe", 
      "ingredients": [
        "",
        ""
      ], 
      "instructions": [
        "",
        ""
      ]
    },
    { 
      "category": 8, 
      "id": 178, 
      "name": "Rhubarb Sauce", 
      "ingredients": [
        "",
        ""
      ], 
      "instructions": [
        "",
        ""
      ]
    },
    { 
      "category": 8, 
      "id": 179, 
      "name": "Caramel Layer Choco-Squares", 
      "ingredients": [
        "",
        ""
      ], 
      "instructions": [
        "",
        ""
      ]
    },
    { 
      "category": 8, 
      "id": 180, 
      "name": "Holly's Apple Bars", 
      "ingredients": [
        "",
        ""
      ], 
      "instructions": [
        "",
        ""
      ]
    },
    { 
      "category": 8, 
      "id": 181, 
      "name": "Brownies with Peanut Butter Frosting", 
      "ingredients": [
        "",
        ""
      ], 
      "instructions": [
        "",
        ""
      ]
    },
    { 
      "category": 8, 
      "id": 182, 
      "name": "7 Layer Bars", 
      "ingredients": [
        "",
        ""
      ], 
      "instructions": [
        "",
        ""
      ]
    },
    { 
      "category": 8, 
      "id": 183, 
      "name": "Gingerbread Bars", 
      "ingredients": [
        "",
        ""
      ], 
      "instructions": [
        "",
        ""
      ]
    },
    { 
      "category": 8, 
      "id": 184, 
      "name": "Carol's No-Bake Cookies", 
      "ingredients": [
        "",
        ""
      ], 
      "instructions": [
        "",
        ""
      ]
    },
    { 
      "category": 8, 
      "id": 185, 
      "name": "Aunt Ollie's Butter Scotch Icebox Cookies", 
      "ingredients": [
        "",
        ""
      ], 
      "instructions": [
        "",
        ""
      ]
    },
    { 
      "category": 8, 
      "id": 186, 
      "name": "Aunt Jennie's Sugar Cookie", 
      "ingredients": [
        "",
        ""
      ], 
      "instructions": [
        "",
        ""
      ]
    },
    { 
      "category": 8, 
      "id": 187, 
      "name": "Peppermint Meringue Kisses", 
      "ingredients": [
        "",
        ""
      ], 
      "instructions": [
        "",
        ""
      ]
    },
    { 
      "category": 8, 
      "id": 188, 
      "name": "Ginger Snaps", 
      "ingredients": [
        "",
        ""
      ], 
      "instructions": [
        "",
        ""
      ]
    },
    { 
      "category": 8, 
      "id": 189, 
      "name": "Pecan Shorts", 
      "ingredients": [
        "",
        ""
      ], 
      "instructions": [
        "",
        ""
      ]
    },
    { 
      "category": 8, 
      "id": 190, 
      "name": "Molasses Cookies", 
      "ingredients": [
        "",
        ""
      ], 
      "instructions": [
        "",
        ""
      ]
    },
    { 
      "category": 8, 
      "id": 191, 
      "name": "Thumbprints - Butterballs", 
      "ingredients": [
        "",
        ""
      ], 
      "instructions": [
        "",
        ""
      ]
    },
    { 
      "category": 8, 
      "id": 192, 
      "name": "Swedish Heirlooms", 
      "ingredients": [
        "",
        ""
      ], 
      "instructions": [
        "",
        ""
      ]
    },
    { 
      "category": 8, 
      "id": 193, 
      "name": "Peanut Butter Cookies", 
      "ingredients": [
        "",
        ""
      ], 
      "instructions": [
        "",
        ""
      ]
    },
    { 
      "category": 8, 
      "id": 194, 
      "name": "Easy Apple Crisp", 
      "ingredients": [
        "",
        ""
      ], 
      "instructions": [
        "",
        ""
      ]
    },
    { 
      "category": 8, 
      "id": 195, 
      "name": "Sandbaker", 
      "ingredients": [
        "",
        ""
      ], 
      "instructions": [
        "",
        ""
      ]
    },
    { 
      "category": 8, 
      "id": 196, 
      "name": "Linda's Five Flavor Cake", 
      "ingredients": [
        "",
        ""
      ], 
      "instructions": [
        "",
        ""
      ]
    },
    { 
      "category": 8, 
      "id": 197, 
      "name": "Italian Dunkers", 
      "ingredients": [
        "",
        ""
      ], 
      "instructions": [
        "",
        ""
      ]
    },
    { 
      "category": 8, 
      "id": 198, 
      "name": "Apple Cranberry Cobbler", 
      "ingredients": [
        "",
        ""
      ], 
      "instructions": [
        "",
        ""
      ]
    },
    { 
      "category": 8, 
      "id": 199, 
      "name": "Glorified Ginger Cake", 
      "ingredients": [
        "",
        ""
      ], 
      "instructions": [
        "",
        ""
      ]
    },
    { 
      "category": 8, 
      "id": 200, 
      "name": "Rosy Rhubarb Cake", 
      "ingredients": [
        "",
        ""
      ], 
      "instructions": [
        "",
        ""
      ]
    },
    { 
      "category": 8, 
      "id": 201, 
      "name": "Holly's Twinkies", 
      "ingredients": [
        "",
        ""
      ], 
      "instructions": [
        "",
        ""
      ]
    },
    { 
      "category": 8, 
      "id": 202, 
      "name": "Pinchme Cake (Monkey Bread)", 
      "ingredients": [
        "",
        ""
      ], 
      "instructions": [
        "",
        ""
      ]
    },
    { 
      "category": 8, 
      "id": 203, 
      "name": "Linda's Cream Cheese Pound Cake", 
      "ingredients": [
        "",
        ""
      ], 
      "instructions": [
        "",
        ""
      ]
    },
    { 
      "category": 8, 
      "id": 204, 
      "name": "Grandma Conklyn's Apple Cake", 
      "ingredients": [
        "",
        ""
      ], 
      "instructions": [
        "",
        ""
      ]
    },
    { 
      "category": 8, 
      "id": 205, 
      "name": "Mom's Sour Cream Cookies", 
      "ingredients": [
        "",
        ""
      ], 
      "instructions": [
        "",
        ""
      ]
    },
    { 
      "category": 8, 
      "id": 206, 
      "name": "Ohio Buckeye's", 
      "ingredients": [
        "",
        ""
      ], 
      "instructions": [
        "",
        ""
      ]
    },
    { 
      "category": 8, 
      "id": 207, 
      "name": "Chocolate Ice Box Torte", 
      "ingredients": [
        "",
        ""
      ], 
      "instructions": [
        "",
        ""
      ]
    },
    { 
      "category": 8, 
      "id": 208, 
      "name": "Company Cheese Cake", 
      "ingredients": [
        "",
        ""
      ], 
      "instructions": [
        "",
        ""
      ]
    },
    { 
      "category": 8, 
      "id": 209, 
      "name": "Blitz Torte", 
      "ingredients": [
        "",
        ""
      ], 
      "instructions": [
        "",
        ""
      ]
    },
    { 
      "category": 8, 
      "id": 210, 
      "name": "Petite Cheese Cakes", 
      "ingredients": [
        "",
        ""
      ], 
      "instructions": [
        "",
        ""
      ]
    },
    { 
      "category": 8, 
      "id": 211, 
      "name": "Puppy Chow", 
      "ingredients": [
        "",
        ""
      ], 
      "instructions": [
        "",
        ""
      ]
    },
    { 
      "category": 8, 
      "id": 212, 
      "name": "Elizabeth's Rhubarb Cake", 
      "ingredients": [
        "",
        ""
      ], 
      "instructions": [
        "",
        ""
      ]
    },
    { 
      "category": 8, 
      "id": 213, 
      "name": "Spice Cake in a Jar", 
      "ingredients": [
        "",
        ""
      ], 
      "instructions": [
        "",
        ""
      ]
    },
    { 
      "category": 8, 
      "id": 214, 
      "name": "Mom's Cheese Torte", 
      "ingredients": [
        "",
        ""
      ], 
      "instructions": [
        "",
        ""
      ]
    },
    { 
      "category": 8, 
      "id": 215, 
      "name": "Apple Delight", 
      "ingredients": [
        "",
        ""
      ], 
      "instructions": [
        "",
        ""
      ]
    },
    { 
      "category": 8, 
      "id": 216, 
      "name": "Meringue", 
      "ingredients": [
        "",
        ""
      ], 
      "instructions": [
        "",
        ""
      ]
    },
    { 
      "category": 8, 
      "id": 217, 
      "name": "Jello Torte", 
      "ingredients": [
        "",
        ""
      ], 
      "instructions": [
        "",
        ""
      ]
    },
    { 
      "category": 8, 
      "id": 218, 
      "name": "Holly's Chocolate Eclair Torte", 
      "ingredients": [
        "",
        ""
      ], 
      "instructions": [
        "",
        ""
      ]
    },
    { 
      "category": 8, 
      "id": 219, 
      "name": "Luscious 4 Layer Pumpkin Cake", 
      "ingredients": [
        "",
        ""
      ], 
      "instructions": [
        "",
        ""
      ]
    },
    { 
      "category": 8, 
      "id": 220, 
      "name": "Aunt Jennie's Chocolate Pie", 
      "ingredients": [
        "",
        ""
      ], 
      "instructions": [
        "",
        ""
      ]
    },
    { 
      "category": 8, 
      "id": 221, 
      "name": "Pumpkin Torte", 
      "ingredients": [
        "",
        ""
      ], 
      "instructions": [
        "",
        ""
      ]
    },
    { 
      "category": 8, 
      "id": 222, 
      "name": "Holly's Apple Pizza Pie", 
      "ingredients": [
        "",
        ""
      ], 
      "instructions": [
        "",
        ""
      ]
    },
    { 
      "category": 8, 
      "id": 223, 
      "name": "Pumkin Pie", 
      "ingredients": [
        "",
        ""
      ], 
      "instructions": [
        "",
        ""
      ]
    },
    { 
      "category": 8, 
      "id": 224, 
      "name": "Aunt Jenny's Lemon Meringue Pie", 
      "ingredients": [
        "",
        ""
      ], 
      "instructions": [
        "",
        ""
      ]
    },
    { 
      "category": 8, 
      "id": 225, 
      "name": "Fruit Pizza", 
      "ingredients": [
        "",
        ""
      ], 
      "instructions": [
        "",
        ""
      ]
    },
    { 
      "category": 8, 
      "id": 226, 
      "name": "Holly's Chocolate Chip Brittle", 
      "ingredients": [
        "",
        ""
      ], 
      "instructions": [
        "",
        ""
      ]
    },
    { 
      "category": 8, 
      "id": 227, 
      "name": "Chocolate Mousse Pie", 
      "ingredients": [
        "",
        ""
      ], 
      "instructions": [
        "",
        ""
      ]
    },
    { 
      "category": 8, 
      "id": 228, 
      "name": "Holly's Peanut Butter Balls", 
      "ingredients": [
        "",
        ""
      ], 
      "instructions": [
        "",
        ""
      ]
    },
    { 
      "category": 8, 
      "id": 229, 
      "name": "Yummy Chocolate Brownies", 
      "ingredients": [
        "",
        ""
      ], 
      "instructions": [
        "",
        ""
      ]
    },
    { 
      "category": 8, 
      "id": 230, 
      "name": "Penny's Time-Saving Caramels", 
      "ingredients": [
        "",
        ""
      ], 
      "instructions": [
        "",
        ""
      ]
    },
    { 
      "category": 8, 
      "id": 231, 
      "name": "Peanut Butter Temptations", 
      "ingredients": [
        "",
        ""
      ], 
      "instructions": [
        "",
        ""
      ]
    },
    { 
      "category": 8, 
      "id": 232, 
      "name": "Oven-Baked Caramel Corn", 
      "ingredients": [
        "",
        ""
      ], 
      "instructions": [
        "",
        ""
      ]
    },
    { 
      "category": 8, 
      "id": 233, 
      "name": "Buttery Toffee", 
      "ingredients": [
        "",
        ""
      ], 
      "instructions": [
        "",
        ""
      ]
    },
    { 
      "category": 8, 
      "id": 234, 
      "name": "Paul and Di's Hand Dipped Creams", 
      "ingredients": [
        "",
        ""
      ], 
      "instructions": [
        "",
        ""
      ]
    },
    { 
      "category": 8, 
      "id": 235, 
      "name": "Fudge", 
      "ingredients": [
        "",
        ""
      ], 
      "instructions": [
        "",
        ""
      ]
    },
    { 
      "category": 8, 
      "id": 236, 
      "name": "Mints", 
      "ingredients": [
        "",
        ""
      ], 
      "instructions": [
        "",
        ""
      ]
    },
    { 
      "category": 8, 
      "id": 237, 
      "name": "Krantz", 
      "ingredients": [
        "",
        ""
      ], 
      "instructions": [
        "",
        ""
      ]
    },
    {
      "category": 9, 
      "id": 238, 
      "name": "Kathy's Play Dough", 
      "ingredients": [
        "",
        ""
      ], 
      "instructions": [
        "",
        ""
      ]
    },
    { 
      "category": 9, 
      "id": 239, 
      "name": "Mac's Window Cleaning Solution", 
      "ingredients": [
        "",
        ""
      ], 
      "instructions": [
        "",
        ""
      ]
     }
  ]
}